tunein/__init__.py
tunein/parse.py
tunein/version.py
tunein/xml_helper.py
tunein-0.0.2.dist-info/LICENSE
tunein-0.0.2.dist-info/METADATA
tunein-0.0.2.dist-info/WHEEL
tunein-0.0.2.dist-info/top_level.txt
tunein-0.0.2.dist-info/RECORD
