Metadata-Version: 2.1
Name: tunein
Version: 0.0.2
Summary: TuneIn radio api
Home-page: https://github.com/OpenJarbas/tunein
Author: JarbasAi
Author-email: UNKNOWN
License: Apache-2.0
Keywords: TuneIn internet radio
Platform: UNKNOWN
Requires-Dist: requests
